README.md
setup.cfg
setup.py
bin/musa
musa/__init__.py
musa/cli.py
musa/defaults.py
musa/transcoder.py
musa.egg-info/PKG-INFO
musa.egg-info/SOURCES.txt
musa.egg-info/dependency_links.txt
musa.egg-info/requires.txt
musa.egg-info/top_level.txt
test/__init__.py
test/test_metadata.py
test/test_tree.py