Metadata-Version: 1.0
Name: musa
Version: 4.5.0
Summary: Soundforest module CLI for music tagging and library management
Home-page: https://github.com/hile/musa
Author: Ilkka Tuohela
Author-email: hile@iki.fi
License: PSF
Keywords: music library tag management
Platform: UNKNOWN
